setup.cfg
setup.py
multiarow/__init__.py
multiarow/arow.py
multiarow.egg-info/PKG-INFO
multiarow.egg-info/SOURCES.txt
multiarow.egg-info/dependency_links.txt
multiarow.egg-info/pbr.json
multiarow.egg-info/requires.txt
multiarow.egg-info/top_level.txt