Metadata-Version: 1.1
Name: multiarow
Version: 0.2
Summary: Multiclass AROW implementation
Home-page: https://github.com/AlpacaDB/multiarow
Author: AlpacaDB, Inc.
Author-email: UNKNOWN
License: MIT
Keywords: online learning multiclass
Platform: UNKNOWN
Classifier: Development Status :: 3 - Alpha
Classifier: Intended Audience :: Information Technology
Classifier: License :: OSI Approved :: MIT License
Classifier: Programming Language :: Python :: 2.7
